{
	"description": "项目配置文件。",
	"packOptions": {
		"ignore": []
	},
	"setting": {
		"urlCheck": true,
		"es6": true,
		"postcss": true,
		"minified": true,
		"newFeature": true
	},
	"compileType": "miniprogram",
	"libVersion": "2.0.4",
	"appid": "wx3487bb98a8a5510e",
	"projectname": "%E9%AA%B0%E5%AD%90%E7%BF%BB%E8%AF%91",
	"isGameTourist": false,
	"condition": {
		"search": {
			"current": -1,
			"list": []
		},
		"conversation": {
			"current": -1,
			"list": []
		},
		"plugin": {
			"current": -1,
			"list": []
		},
		"game": {
			"currentL": -1,
			"list": []
		},
		"miniprogram": {
			"current": 0,
			"list": [
				{
					"id": 0,
					"name": "测试倒计时",
					"pathName": "pages/counter/counter",
					"query": "random=3"
				}
			]
		}
	}
}